xsptools/__init__.py
xsptools/__version__.py
xsptools/binning/__init__.py
xsptools/binning/src/__init__.py
xsptools/binning/src/helpers.py
xsptools/binning/src/processor.py
xsptools-1.0.0.dist-info/licenses/LICENSE
xsptools-1.0.0.dist-info/METADATA
xsptools-1.0.0.dist-info/WHEEL
xsptools-1.0.0.dist-info/top_level.txt
xsptools-1.0.0.dist-info/RECORD
