Metadata-Version: 2.4
Name: xsptools
Version: 1.0.0
Summary: xsptools - Collection of python packages to process data originating from X-Spectrum detectors
Author-email: Emanuele Besana <emanuele.besana@x-spectrum.de>
Maintainer-email: Emanuele Besana <emanuele.besana@x-spectrum.de>
License: Copyright (c) 2025 X-Spectrum GmbH, Germany. All Rights Reserved.
Classifier: Programming Language :: Python :: 3
Classifier: License :: OSI Approved :: BSD License
Classifier: Operating System :: OS Independent
Classifier: Topic :: Scientific/Engineering :: Physics
Requires-Python: >=3.8
License-File: LICENSE
Requires-Dist: numpy>=1.6.0
Dynamic: license-file
